djangocms_jq/__init__.py
djangocms_jq/cms_plugins.py
djangocms_jq/fetcher.py
djangocms_jq/forms.py
djangocms_jq/models.py
djangocms_jq/utils.py
djangocms_jq/locale/cs/LC_MESSAGES/django.mo
djangocms_jq/locale/cs/LC_MESSAGES/django.po
djangocms_jq/migrations/0001_initial.py
djangocms_jq/migrations/0002_showvalue_show_when_missing.py
djangocms_jq/migrations/0003_query_wrapper_textfield.py
djangocms_jq/migrations/__init__.py
djangocms_jq/templates/admin/djangocms_jq/change_form.html
djangocms_jq/templates/djangocms_jq/plugin.html
djangocms_jq-1.1.3.dist-info/METADATA
djangocms_jq-1.1.3.dist-info/WHEEL
djangocms_jq-1.1.3.dist-info/top_level.txt
djangocms_jq-1.1.3.dist-info/RECORD
